odoo/addons/account_payment_credit_card/README.rst
odoo/addons/account_payment_credit_card/__init__.py
odoo/addons/account_payment_credit_card/__manifest__.py
odoo/addons/account_payment_credit_card/i18n/account_payment_credit_card.pot
odoo/addons/account_payment_credit_card/i18n/es.po
odoo/addons/account_payment_credit_card/i18n/it.po
odoo/addons/account_payment_credit_card/i18n/nl.po
odoo/addons/account_payment_credit_card/i18n/pt_BR.po
odoo/addons/account_payment_credit_card/models/__init__.py
odoo/addons/account_payment_credit_card/models/account_journal.py
odoo/addons/account_payment_credit_card/models/account_move.py
odoo/addons/account_payment_credit_card/readme/CONFIGURE.rst
odoo/addons/account_payment_credit_card/readme/CONTRIBUTORS.rst
odoo/addons/account_payment_credit_card/readme/DESCRIPTION.rst
odoo/addons/account_payment_credit_card/readme/USAGE.rst
odoo/addons/account_payment_credit_card/static/description/icon.png
odoo/addons/account_payment_credit_card/static/description/index.html
odoo/addons/account_payment_credit_card/tests/__init__.py
odoo/addons/account_payment_credit_card/tests/test_payment_credit_card.py
odoo/addons/account_payment_credit_card/views/account_view.xml
odoo_addon_account_payment_credit_card-16.0.1.0.1.dist-info/METADATA
odoo_addon_account_payment_credit_card-16.0.1.0.1.dist-info/WHEEL
odoo_addon_account_payment_credit_card-16.0.1.0.1.dist-info/top_level.txt
odoo_addon_account_payment_credit_card-16.0.1.0.1.dist-info/RECORD
